Workbook

Sheet Importante
A2: Aviso Importante
A4: Região de SP desconsiderar a coluna de ST da aba pedidos
A6: Essa planilha não é válida para clientes do Simples Nacional

Sheet FOLHA DE PEDIDO 
S2: À Vista | T2: 119 | U2: AC
S3: 14 | U3: AL
S4: 21 | U4: AM
S5: 28 | U5: AP
F6: RO | S6: 35 | U6: BA
S7: 42 | U7: CE
G8: Inserir 20% de desconto em todos os itens | S8: 49 | U8: DF
C9: 119 | F9: À Vista | G9: R$ 3.000,00: pequeno e médio varejo | S9: 56 | U9: ES
G10: R$ 5.000,00: supermercados e grandes redes | S10: 60 | U10: RO
G11: Observação do pedido: | S11: 75 | U11: MA
C12: =SUM($N$21:$N$328) -> 0 | S12: 90 | U12: MG
U13: MS
U14: MT
U15: PA
U16: PB
U17: PE
U18: PI
U19: PR
B20: CÓDIGO PRODUTO | C20: DESCRIÇÃO | D20: M.V. | E20: COR | F20: QTDE | G20: PREÇO TABELA | H20: DESC. | I20: PREÇO UNI. | J20: IPI | K20: ST | L20: PREÇO C/ IPI | M20: PREÇO C/ ST | N20: VALOR LÍQ. | O20: VALOR BRUTO | P20: NCM | U20: RJ
C21: =IFERROR((IF(B21="","",IF($F$6="","Informar UF / Tabela / Prazo de Pagamento",IF($F$9="","Informar UF / Tabela / Prazo de Pagamento",IF($C$9="","Informar UF / Tabela / Prazo de Pagamento",VLOOKUP(B21,'Tabela 130 '!$A$5:$T$1001,2,FALSE)))))),"REF. NÃO CADASTRADA NA TABELA") | D21: =IF('FOLHA DE PEDIDO '!B21="","",IF(C21="REF. NÃO CADASTRADA NA TABELA","",VLOOKUP(B21,'Tabela 130 '!$A$5:$AI$801,3,FALSE))) | G21: =IFERROR(IF(C21="REF. NÃO CADASTRADA NA TABELA","",IF($C$9="","",IF($F$9="","",IF(B21="","",IF($C$9=119,VLOOKUP(B21,'Tabela 130 '!$A$5:$T$2711,MATCH($F$9,'Tabela 130 '!$A$5:$T$5,0),FALSE),IF($C$9=553,VLOOKUP(B21,#REF!,MATCH($F$9,#REF!,0),FALSE),IF($C$9=552,VLOOKUP(B21,#REF!,MATCH($F$9,#REF!,0),FALSE),IF($C$9=551,VLOOKUP(B21,#REF!,MATCH($F$9,#REF!,0),FALSE))))))))),"REF. NÃO CADASTRADA NA TABELA") | H21: 0.2 | I21: =IFERROR(IF(B21=0,"",(G21-(G21*H21))),"") | J21: =IF(B21="","",IF(C21="REF. NÃO CADASTRADA NA TABELA","",VLOOKUP(B21,#REF!,7,FALSE))) | K21: =IF($F$6="","",IF(B21="","",IF(C21="REF. NÃO CADASTRADA NA TABELA","",IFERROR(VLOOKUP(B21,#REF!,VLOOKUP($F$6,'BASE CONTÁBIL'!N:O,2,FALSE),FALSE),0)))) | L21: =IFERROR(I21*(1+J21%),"") | M21: =IFERROR(IF(B21="","",L21*(1+K21)),"") | N21: =IFERROR(IF(B21="","",IF(F21="","",F21*I21)),"") | O21: =IFERROR(IF(B21="","",IF(F21="","",M21*F21)),"") | P21: =VLOOKUP(B21,#REF!,17,FALSE) -> #REF! | U21: SP
C22: =IFERROR((IF(B22="","",IF($F$6="","Informar UF / Tabela / Prazo de Pagamento",IF($F$9="","Informar UF / Tabela / Prazo de Pagamento",IF($C$9="","Informar UF / Tabela / Prazo de Pagamento",VLOOKUP(B22,'Tabela 130 '!$A$5:$T$1001,2,FALSE)))))),"REF. NÃO CADASTRADA NA TABELA") | D22: =IF('FOLHA DE PEDIDO '!B22="","",IF(C22="REF. NÃO CADASTRADA NA TABELA","",VLOOKUP(B22,'Tabela 130 '!$A$5:$AI$801,3,FALSE))) | G22: =IFERROR(IF(C22="REF. NÃO CADASTRADA NA TABELA","",IF($C$9="","",IF($F$9="","",IF(B22="","",IF($C$9=119,VLOOKUP(B22,'Tabela 130 '!$A$5:$T$2711,MATCH($F$9,'Tabela 130 '!$A$5:$T$5,0),FALSE),IF($C$9=553,VLOOKUP(B22,#REF!,MATCH($F$9,#REF!,0),FALSE),IF($C$9=552,VLOOKUP(B22,#REF!,MATCH($F$9,#REF!,0),FALSE),IF($C$9=551,VLOOKUP(B22,#REF!,MATCH($F$9,#REF!,0),FALSE))))))))),"REF. NÃO CADASTRADA NA TABELA") | I22: =IFERROR(IF(B22=0,"",(G22-(G22*H22))),"") | J22: =IF(B22="","",IF(C22="REF. NÃO CADASTRADA NA TABELA","",VLOOKUP(B22,#REF!,7,FALSE))) | K22: =IF($F$6="","",IF(B22="","",IF(C22="REF. NÃO CADASTRADA NA TABELA","",IFERROR(VLOOKUP(B22,#REF!,VLOOKUP($F$6,'BASE CONTÁBIL'!N:O,2,FALSE),FALSE),0)))) | L22: =IFERROR(I22*(1+J22%),"") | M22: =IFERROR(IF(B22="","",L22*(1+K22)),"") | N22: =IFERROR(IF(B22="","",IF(F22="","",F22*I22)),"") | O22: =IFERROR(IF(B22="","",IF(F22="","",M22*F22)),"") | P22: =VLOOKUP(B22,#REF!,17,FALSE) -> #REF! | U22: TO
C23: =IFERROR((IF(B23="","",IF($F$6="","Informar UF / Tabela / Prazo de Pagamento",IF($F$9="","Informar UF / Tabela / Prazo de Pagamento",IF($C$9="","Informar UF / Tabela / Prazo de Pagamento",VLOOKUP(B23,'Tabela 130 '!$A$5:$T$1001,2,FALSE)))))),"REF. NÃO CADASTRADA NA TABELA") | D23: =IF('FOLHA DE PEDIDO '!B23="","",IF(C23="REF. NÃO CADASTRADA NA TABELA","",VLOOKUP(B23,'Tabela 130 '!$A$5:$AI$801,3,FALSE))) | G23: =IFERROR(IF(C23="REF. NÃO CADASTRADA NA TABELA","",IF($C$9="","",IF($F$9="","",IF(B23="","",IF($C$9=119,VLOOKUP(B23,'Tabela 130 '!$A$5:$T$2711,MATCH($F$9,'Tabela 130 '!$A$5:$T$5,0),FALSE),IF($C$9=553,VLOOKUP(B23,#REF!,MATCH($F$9,#REF!,0),FALSE),IF($C$9=552,VLOOKUP(B23,#REF!,MATCH($F$9,#REF!,0),FALSE),IF($C$9=551,VLOOKUP(B23,#REF!,MATCH($F$9,#REF!,0),FALSE))))))))),"REF. NÃO CADASTRADA NA TABELA") | I23: =IFERROR(IF(B23=0,"",(G23-(G23*H23))),"") | J23: =IF(B23="","",IF(C23="REF. NÃO CADASTRADA NA TABELA","",VLOOKUP(B23,#REF!,7,FALSE))) | K23: =IF($F$6="","",IF(B23="","",IF(C23="REF. NÃO CADASTRADA NA TABELA","",IFERROR(VLOOKUP(B23,#REF!,VLOOKUP($F$6,'BASE CONTÁBIL'!N:O,2,FALSE),FALSE),0)))) | L23: =IFERROR(I23*(1+J23%),"") | M23: =IFERROR(IF(B23="","",L23*(1+K23)),"") | N23: =IFERROR(IF(B23="","",IF(F23="","",F23*I23)),"") | O23: =IFERROR(IF(B23="","",IF(F23="","",M23*F23)),"") | P23: =VLOOKUP(B23,#REF!,17,FALSE) -> #REF!
C24: =IFERROR((IF(B24="","",IF($F$6="","Informar UF / Tabela / Prazo de Pagamento",IF($F$9="","Informar UF / Tabela / Prazo de Pagamento",IF($C$9="","Informar UF / Tabela / Prazo de Pagamento",VLOOKUP(B24,'Tabela 130 '!$A$5:$T$1001,2,FALSE)))))),"REF. NÃO CADASTRADA NA TABELA") | D24: =IF('FOLHA DE PEDIDO '!B24="","",IF(C24="REF. NÃO CADASTRADA NA TABELA","",VLOOKUP(B24,'Tabela 130 '!$A$5:$AI$801,3,FALSE))) | G24: =IFERROR(IF(C24="REF. NÃO CADASTRADA NA TABELA","",IF($C$9="","",IF($F$9="","",IF(B24="","",IF($C$9=119,VLOOKUP(B24,'Tabela 130 '!$A$5:$T$2711,MATCH($F$9,'Tabela 130 '!$A$5:$T$5,0),FALSE),IF($C$9=553,VLOOKUP(B24,#REF!,MATCH($F$9,#REF!,0),FALSE),IF($C$9=552,VLOOKUP(B24,#REF!,MATCH($F$9,#REF!,0),FALSE),IF($C$9=551,VLOOKUP(B24,#REF!,MATCH($F$9,#REF!,0),FALSE))))))))),"REF. NÃO CADASTRADA NA TABELA") | I24: =IFERROR(IF(B24=0,"",(G24-(G24*H24))),"") | J24: =IF(B24="","",IF(C24="REF. NÃO CADASTRADA NA TABELA","",VLOOKUP(B24,#REF!,7,FALSE))) | K24: =IF($F$6="","",IF(B24="","",IF(C24="REF. NÃO CADASTRADA NA TABELA","",IFERROR(VLOOKUP(B24,#REF!,VLOOKUP($F$6,'BASE CONTÁBIL'!N:O,2,FALSE),FALSE),0)))) | L24: =IFERROR(I24*(1+J24%),"") | M24: =IFERROR(IF(B24="","",L24*(1+K24)),"") | N24: =IFERROR(IF(B24="","",IF(F24="","",F24*I24)),"") | O24: =IFERROR(IF(B24="","",IF(F24="","",M24*F24)),"") | P24: =VLOOKUP(B24,#REF!,17,FALSE) -> #REF!
G25: =IFERROR(IF(C25="REF. NÃO CADASTRADA NA TABELA","",IF($C$9="","",IF($F$9="","",IF(B25="","",IF($C$9=119,VLOOKUP(B25,'Tabela 130 '!$A$5:$T$2711,MATCH($F$9,'Tabela 130 '!$A$5:$T$5,0),FALSE),IF($C$9=553,VLOOKUP(B25,#REF!,MATCH($F$9,#REF!,0),FALSE),IF($C$9=552,VLOOKUP(B25,#REF!,MATCH($F$9,#REF!,0),FALSE),IF($C$9=551,VLOOKUP(B25,#REF!,MATCH($F$9,#REF!,0),FALSE))))))))),"REF. NÃO CADASTRADA NA TABELA") | I25: =IFERROR(IF(B25=0,"",(G25-(G25*H25))),"") | J25: =IF(B25="","",IF(C25="REF. NÃO CADASTRADA NA TABELA","",VLOOKUP(B25,#REF!,7,FALSE))) | K25: =IF($F$6="","",IF(B25="","",IF(C25="REF. NÃO CADASTRADA NA TABELA","",IFERROR(VLOOKUP(B25,#REF!,VLOOKUP($F$6,'BASE CONTÁBIL'!N:O,2,FALSE),FALSE),0)))) | L25: =IFERROR(I25*(1+J25%),"") | M25: =IFERROR(IF(B25="","",L25*(1+K25)),"") | N25: =IFERROR(IF(B25="","",IF(F25="","",F25*I25)),"") | O25: =IFERROR(IF(B25="","",IF(F25="","",M25*F25)),"") | P25: =VLOOKUP(B25,#REF!,17,FALSE) -> #REF!
C26: =IFERROR((IF(B26="","",IF($F$6="","Informar UF / Tabela / Prazo de Pagamento",IF($F$9="","Informar UF / Tabela / Prazo de Pagamento",IF($C$9="","Informar UF / Tabela / Prazo de Pagamento",VLOOKUP(B26,'Tabela 130 '!$A$5:$T$1001,2,FALSE)))))),"REF. NÃO CADASTRADA NA TABELA") | D26: =IF('FOLHA DE PEDIDO '!B26="","",IF(C26="REF. NÃO CADASTRADA NA TABELA","",VLOOKUP(B26,'Tabela 130 '!$A$5:$AI$801,3,FALSE))) | G26: =IFERROR(IF(C26="REF. NÃO CADASTRADA NA TABELA","",IF($C$9="","",IF($F$9="","",IF(B26="","",IF($C$9=119,VLOOKUP(B26,'Tabela 130 '!$A$5:$T$2711,MATCH($F$9,'Tabela 130 '!$A$5:$T$5,0),FALSE),IF($C$9=553,VLOOKUP(B26,#REF!,MATCH($F$9,#REF!,0),FALSE),IF($C$9=552,VLOOKUP(B26,#REF!,MATCH($F$9,#REF!,0),FALSE),IF($C$9=551,VLOOKUP(B26,#REF!,MATCH($F$9,#REF!,0),FALSE))))))))),"REF. NÃO CADASTRADA NA TABELA") | I26: =IFERROR(IF(B26=0,"",(G26-(G26*H26))),"") | J26: =IF(B26="","",IF(C26="REF. NÃO CADASTRADA NA TABELA","",VLOOKUP(B26,#REF!,7,FALSE))) | K26: =IF($F$6="","",IF(B26="","",IF(C26="REF. NÃO CADASTRADA NA TABELA","",IFERROR(VLOOKUP(B26,#REF!,VLOOKUP($F$6,'BASE CONTÁBIL'!N:O,2,FALSE),FALSE),0)))) | L26: =IFERROR(I26*(1+J26%),"") | M26: =IFERROR(IF(B26="","",L26*(1+K26)),"") | N26: =IFERROR(IF(B26="","",IF(F26="","",F26*I26)),"") | O26: =IFERROR(IF(B26="","",IF(F26="","",M26*F26)),"") | P26: =VLOOKUP(B26,#REF!,17,FALSE) -> #REF!
C27: =IFERROR((IF(B27="","",IF($F$6="","Informar UF / Tabela / Prazo de Pagamento",IF($F$9="","Informar UF / Tabela / Prazo de Pagamento",IF($C$9="","Informar UF / Tabela / Prazo de Pagamento",VLOOKUP(B27,'Tabela 130 '!$A$5:$T$1001,2,FALSE)))))),"REF. NÃO CADASTRADA NA TABELA") | D27: =IF('FOLHA DE PEDIDO '!B27="","",IF(C27="REF. NÃO CADASTRADA NA TABELA","",VLOOKUP(B27,'Tabela 130 '!$A$5:$AI$801,3,FALSE))) | G27: =IFERROR(IF(C27="REF. NÃO CADASTRADA NA TABELA","",IF($C$9="","",IF($F$9="","",IF(B27="","",IF($C$9=119,VLOOKUP(B27,'Tabela 130 '!$A$5:$T$2711,MATCH($F$9,'Tabela 130 '!$A$5:$T$5,0),FALSE),IF($C$9=553,VLOOKUP(B27,#REF!,MATCH($F$9,#REF!,0),FALSE),IF($C$9=552,VLOOKUP(B27,#REF!,MATCH($F$9,#REF!,0),FALSE),IF($C$9=551,VLOOKUP(B27,#REF!,MATCH($F$9,#REF!,0),FALSE))))))))),"REF. NÃO CADASTRADA NA TABELA") | I27: =IFERROR(IF(B27=0,"",(G27-(G27*H27))),"") | J27: =IF(B27="","",IF(C27="REF. NÃO CADASTRADA NA TABELA","",VLOOKUP(B27,#REF!,7,FALSE))) | K27: =IF($F$6="","",IF(B27="","",IF(C27="REF. NÃO CADASTRADA NA TABELA","",IFERROR(VLOOKUP(B27,#REF!,VLOOKUP($F$6,'BASE CONTÁBIL'!N:O,2,FALSE),FALSE),0)))) | L27: =IFERROR(I27*(1+J27%),"") | M27: =IFERROR(IF(B27="","",L27*(1+K27)),"") | N27: =IFERROR(IF(B27="","",IF(F27="","",F27*I27)),"") | O27: =IFERROR(IF(B27="","",IF(F27="","",M27*F27)),"") | P27: =VLOOKUP(B27,#REF!,17,FALSE) -> #REF!
C28: =IFERROR((IF(B28="","",IF($F$6="","Informar UF / Tabela / Prazo de Pagamento",IF($F$9="","Informar UF / Tabela / Prazo de Pagamento",IF($C$9="","Informar UF / Tabela / Prazo de Pagamento",VLOOKUP(B28,'Tabela 130 '!$A$5:$T$1001,2,FALSE)))))),"REF. NÃO CADASTRADA NA TABELA") | D28: =IF('FOLHA DE PEDIDO '!B28="","",IF(C28="REF. NÃO CADASTRADA NA TABELA","",VLOOKUP(B28,'Tabela 130 '!$A$5:$AI$801,3,FALSE))) | G28: =IFERROR(IF(C28="REF. NÃO CADASTRADA NA TABELA","",IF($C$9="","",IF($F$9="","",IF(B28="","",IF($C$9=119,VLOOKUP(B28,'Tabela 130 '!$A$5:$T$2711,MATCH($F$9,'Tabela 130 '!$A$5:$T$5,0),FALSE),IF($C$9=553,VLOOKUP(B28,#REF!,MATCH($F$9,#REF!,0),FALSE),IF($C$9=552,VLOOKUP(B28,#REF!,MATCH($F$9,#REF!,0),FALSE),IF($C$9=551,VLOOKUP(B28,#REF!,MATCH($F$9,#REF!,0),FALSE))))))))),"REF. NÃO CADASTRADA NA TABELA") | I28: =IFERROR(IF(B28=0,"",(G28-(G28*H28))),"") | J28: =IF(B28="","",IF(C28="REF. NÃO CADASTRADA NA TABELA","",VLOOKUP(B28,#REF!,7,FALSE))) | K28: =IF($F$6="","",IF(B28="","",IF(C28="REF. NÃO CADASTRADA NA TABELA","",IFERROR(VLOOKUP(B28,#REF!,VLOOKUP($F$6,'BASE CONTÁBIL'!N:O,2,FALSE),FALSE),0)))) | L28: =IFERROR(I28*(1+J28%),"") | M28: =IFERROR(IF(B28="","",L28*(1+K28)),"") | N28: =IFERROR(IF(B28="","",IF(F28="","",F28*I28)),"") | O28: =IFERROR(IF(B28="","",IF(F28="","",M28*F28)),"") | P28: =VLOOKUP(B28,#REF!,17,FALSE) -> #REF!
C29: =IFERROR((IF(B29="","",IF($F$6="","Informar UF / Tabela / Prazo de Pagamento",IF($F$9="","Informar UF / Tabela / Prazo de Pagamento",IF($C$9="","Informar UF / Tabela / Prazo de Pagamento",VLOOKUP(B29,'Tabela 130 '!$A$5:$T$1001,2,FALSE)))))),"REF. NÃO CADASTRADA NA TABELA") | D29: =IF('FOLHA DE PEDIDO '!B29="","",IF(C29="REF. NÃO CADASTRADA NA TABELA","",VLOOKUP(B29,'Tabela 130 '!$A$5:$AI$801,3,FALSE))) | G29: =IFERROR(IF(C29="REF. NÃO CADASTRADA NA TABELA","",IF($C$9="","",IF($F$9="","",IF(B29="","",IF($C$9=119,VLOOKUP(B29,'Tabela 130 '!$A$5:$T$2711,MATCH($F$9,'Tabela 130 '!$A$5:$T$5,0),FALSE),IF($C$9=553,VLOOKUP(B29,#REF!,MATCH($F$9,#REF!,0),FALSE),IF($C$9=552,VLOOKUP(B29,#REF!,MATCH($F$9,#REF!,0),FALSE),IF($C$9=551,VLOOKUP(B29,#REF!,MATCH($F$9,#REF!,0),FALSE))))))))),"REF. NÃO CADASTRADA NA TABELA") | I29: =IFERROR(IF(B29=0,"",(G29-(G29*H29))),"") | J29: =IF(B29="","",IF(C29="REF. NÃO CADASTRADA NA TABELA","",VLOOKUP(B29,#REF!,7,FALSE))) | K29: =IF($F$6="","",IF(B29="","",IF(C29="REF. NÃO CADASTRADA NA TABELA","",IFERROR(VLOOKUP(B29,#REF!,VLOOKUP($F$6,'BASE CONTÁBIL'!N:O,2,FALSE),FALSE),0)))) | L29: =IFERROR(I29*(1+J29%),"") | M29: =IFERROR(IF(B29="","",L29*(1+K29)),"") | N29: =IFERROR(IF(B29="","",IF(F29="","",F29*I29)),"") | O29: =IFERROR(IF(B29="","",IF(F29="","",M29*F29)),"") | P29: =VLOOKUP(B29,#REF!,17,FALSE) -> #REF!
C30: =IFERROR((IF(B30="","",IF($F$6="","Informar UF / Tabela / Prazo de Pagamento",IF($F$9="","Informar UF / Tabela / Prazo de Pagamento",IF($C$9="","Informar UF / Tabela / Prazo de Pagamento",VLOOKUP(B30,'Tabela 130 '!$A$5:$T$1001,2,FALSE)))))),"REF. NÃO CADASTRADA NA TABELA") | D30: =IF('FOLHA DE PEDIDO '!B30="","",IF(C30="REF. NÃO CADASTRADA NA TABELA","",VLOOKUP(B30,'Tabela 130 '!$A$5:$AI$801,3,FALSE))) | G30: =IFERROR(IF(C30="REF. NÃO CADASTRADA NA TABELA","",IF($C$9="","",IF($F$9="","",IF(B30="","",IF($C$9=119,VLOOKUP(B30,'Tabela 130 '!$A$5:$T$2711,MATCH($F$9,'Tabela 130 '!$A$5:$T$5,0),FALSE),IF($C$9=553,VLOOKUP(B30,#REF!,MATCH($F$9,#REF!,0),FALSE),IF($C$9=552,VLOOKUP(B30,#REF!,MATCH($F$9,#REF!,0),FALSE),IF($C$9=551,VLOOKUP(B30,#REF!,MATCH($F$9,#REF!,0),FALSE))))))))),"REF. NÃO CADASTRADA NA TABELA") | I30: =IFERROR(IF(B30=0,"",(G30-(G30*H30))),"") | J30: =IF(B30="","",IF(C30="REF. NÃO CADASTRADA NA TABELA","",VLOOKUP(B30,#REF!,7,FALSE))) | K30: =IF($F$6="","",IF(B30="","",IF(C30="REF. NÃO CADASTRADA NA TABELA","",IFERROR(VLOOKUP(B30,#REF!,VLOOKUP($F$6,'BASE CONTÁBIL'!N:O,2,FALSE),FALSE),0)))) | L30: =IFERROR(I30*(1+J30%),"") | M30: =IFERROR(IF(B30="","",L30*(1+K30)),"") | N30: =IFERROR(IF(B30="","",IF(F30="","",F30*I30)),"") | O30: =IFERROR(IF(B30="","",IF(F30="","",M30*F30)),"") | P30: =VLOOKUP(B30,#REF!,17,FALSE) -> #REF!
C31: =IFERROR((IF(B31="","",IF($F$6="","Informar UF / Tabela / Prazo de Pagamento",IF($F$9="","Informar UF / Tabela / Prazo de Pagamento",IF($C$9="","Informar UF / Tabela / Prazo de Pagamento",VLOOKUP(B31,'Tabela 130 '!$A$5:$T$1001,2,FALSE)))))),"REF. NÃO CADASTRADA NA TABELA") | D31: =IF('FOLHA DE PEDIDO '!B31="","",IF(C31="REF. NÃO CADASTRADA NA TABELA","",VLOOKUP(B31,'Tabela 130 '!$A$5:$AI$801,3,FALSE))) | G31: =IFERROR(IF(C31="REF. NÃO CADASTRADA NA TABELA","",IF($C$9="","",IF($F$9="","",IF(B31="","",IF($C$9=119,VLOOKUP(B31,'Tabela 130 '!$A$5:$T$2711,MATCH($F$9,'Tabela 130 '!$A$5:$T$5,0),FALSE),IF($C$9=553,VLOOKUP(B31,#REF!,MATCH($F$9,#REF!,0),FALSE),IF($C$9=552,VLOOKUP(B31,#REF!,MATCH($F$9,#REF!,0),FALSE),IF($C$9=551,VLOOKUP(B31,#REF!,MATCH($F$9,#REF!,0),FALSE))))))))),"REF. NÃO CADASTRADA NA TABELA") | I31: =IFERROR(IF(B31=0,"",(G31-(G31*H31))),"") | J31: =IF(B31="","",IF(C31="REF. NÃO CADASTRADA NA TABELA","",VLOOKUP(B31,#REF!,7,FALSE))) | K31: =IF($F$6="","",IF(B31="","",IF(C31="REF. NÃO CADASTRADA NA TABELA","",IFERROR(VLOOKUP(B31,#REF!,VLOOKUP($F$6,'BASE CONTÁBIL'!N:O,2,FALSE),FALSE),0)))) | L31: =IFERROR(I31*(1+J31%),"") | M31: =IFERROR(IF(B31="","",L31*(1+K31)),"") | N31: =IFERROR(IF(B31="","",IF(F31="","",F31*I31)),"") | O31: =IFERROR(IF(B31="","",IF(F31="","",M31*F31)),"") | P31: =VLOOKUP(B31,#REF!,17,FALSE) -> #REF!
C32: =IFERROR((IF(B32="","",IF($F$6="","Informar UF / Tabela / Prazo de Pagamento",IF($F$9="","Informar UF / Tabela / Prazo de Pagamento",IF($C$9="","Informar UF / Tabela / Prazo de Pagamento",VLOOKUP(B32,'Tabela 130 '!$A$5:$T$1001,2,FALSE)))))),"REF. NÃO CADASTRADA NA TABELA") | D32: =IF('FOLHA DE PEDIDO '!B32="","",IF(C32="REF. NÃO CADASTRADA NA TABELA","",VLOOKUP(B32,'Tabela 130 '!$A$5:$AI$801,3,FALSE))) | G32: =IFERROR(IF(C32="REF. NÃO CADASTRADA NA TABELA","",IF($C$9="","",IF($F$9="","",IF(B32="","",IF($C$9=119,VLOOKUP(B32,'Tabela 130 '!$A$5:$T$2711,MATCH($F$9,'Tabela 130 '!$A$5:$T$5,0),FALSE),IF($C$9=553,VLOOKUP(B32,#REF!,MATCH($F$9,#REF!,0),FALSE),IF($C$9=552,VLOOKUP(B32,#REF!,MATCH($F$9,#REF!,0),FALSE),IF($C$9=551,VLOOKUP(B32,#REF!,MATCH($F$9,#REF!,0),FALSE))))))))),"REF. NÃO CADASTRADA NA TABELA") | I32: =IFERROR(IF(B32=0,"",(G32-(G32*H32))),"") | J32: =IF(B32="","",IF(C32="REF. NÃO CADASTRADA NA TABELA","",VLOOKUP(B32,#REF!,7,FALSE))) | K32: =IF($F$6="","",IF(B32="","",IF(C32="REF. NÃO CADASTRADA NA TABELA","",IFERROR(VLOOKUP(B32,#REF!,VLOOKUP($F$6,'BASE CONTÁBIL'!N:O,2,FALSE),FALSE),0)))) | L32: =IFERROR(I32*(1+J32%),"") | M32: =IFERROR(IF(B32="","",L32*(1+K32)),"") | N32: =IFERROR(IF(B32="","",IF(F32="","",F32*I32)),"") | O32: =IFERROR(IF(B32="","",IF(F32="","",M32*F32)),"") | P32: =VLOOKUP(B32,#REF!,17,FALSE) -> #REF!
C33: =IFERROR((IF(B33="","",IF($F$6="","Informar UF / Tabela / Prazo de Pagamento",IF($F$9="","Informar UF / Tabela / Prazo de Pagamento",IF($C$9="","Informar UF / Tabela / Prazo de Pagamento",VLOOKUP(B33,'Tabela 130 '!$A$5:$T$1001,2,FALSE)))))),"REF. NÃO CADASTRADA NA TABELA") | D33: =IF('FOLHA DE PEDIDO '!B33="","",IF(C33="REF. NÃO CADASTRADA NA TABELA","",VLOOKUP(B33,'Tabela 130 '!$A$5:$AI$801,3,FALSE))) | G33: =IFERROR(IF(C33="REF. NÃO CADASTRADA NA TABELA","",IF($C$9="","",IF($F$9="","",IF(B33="","",IF($C$9=119,VLOOKUP(B33,'Tabela 130 '!$A$5:$T$2711,MATCH($F$9,'Tabela 130 '!$A$5:$T$5,0),FALSE),IF($C$9=553,VLOOKUP(B33,#REF!,MATCH($F$9,#REF!,0),FALSE),IF($C$9=552,VLOOKUP(B33,#REF!,MATCH($F$9,#REF!,0),FALSE),IF($C$9=551,VLOOKUP(B33,#REF!,MATCH($F$9,#REF!,0),FALSE))))))))),"REF. NÃO CADASTRADA NA TABELA") | I33: =IFERROR(IF(B33=0,"",(G33-(G33*H33))),"") | J33: =IF(B33="","",IF(C33="REF. NÃO CADASTRADA NA TABELA","",VLOOKUP(B33,#REF!,7,FALSE))) | K33: =IF($F$6="","",IF(B33="","",IF(C33="REF. NÃO CADASTRADA NA TABELA","",IFERROR(VLOOKUP(B33,#REF!,VLOOKUP($F$6,'BASE CONTÁBIL'!N:O,2,FALSE),FALSE),0)))) | L33: =IFERROR(I33*(1+J33%),"") | M33: =IFERROR(IF(B33="","",L33*(1+K33)),"") | N33: =IFERROR(IF(B33="","",IF(F33="","",F33*I33)),"") | O33: =IFERROR(IF(B33="","",IF(F33="","",M33*F33)),"") | P33: =VLOOKUP(B33,#REF!,17,FALSE) -> #REF!
C34: =IFERROR((IF(B34="","",IF($F$6="","Informar UF / Tabela / Prazo de Pagamento",IF($F$9="","Informar UF / Tabela / Prazo de Pagamento",IF($C$9="","Informar UF / Tabela / Prazo de Pagamento",VLOOKUP(B34,'Tabela 130 '!$A$5:$T$1001,2,FALSE)))))),"REF. NÃO CADASTRADA NA TABELA") | D34: =IF('FOLHA DE PEDIDO '!B34="","",IF(C34="REF. NÃO CADASTRADA NA TABELA","",VLOOKUP(B34,'Tabela 130 '!$A$5:$AI$801,3,FALSE))) | G34: =IFERROR(IF(C34="REF. NÃO CADASTRADA NA TABELA","",IF($C$9="","",IF($F$9="","",IF(B34="","",IF($C$9=119,VLOOKUP(B34,'Tabela 130 '!$A$5:$T$2711,MATCH($F$9,'Tabela 130 '!$A$5:$T$5,0),FALSE),IF($C$9=553,VLOOKUP(B34,#REF!,MATCH($F$9,#REF!,0),FALSE),IF($C$9=552,VLOOKUP(B34,#REF!,MATCH($F$9,#REF!,0),FALSE),IF($C$9=551,VLOOKUP(B34,#REF!,MATCH($F$9,#REF!,0),FALSE))))))))),"REF. NÃO CADASTRADA NA TABELA") | I34: =IFERROR(IF(B34=0,"",(G34-(G34*H34))),"") | J34: =IF(B34="","",IF(C34="REF. NÃO CADASTRADA NA TABELA","",VLOOKUP(B34,#REF!,7,FALSE))) | K34: =IF($F$6="","",IF(B34="","",IF(C34="REF. NÃO CADASTRADA NA TABELA","",IFERROR(VLOOKUP(B34,#REF!,VLOOKUP($F$6,'BASE CONTÁBIL'!N:O,2,FALSE),FALSE),0)))) | L34: =IFERROR(I34*(1+J34%),"") | M34: =IFERROR(IF(B34="","",L34*(1+K34)),"") | N34: =IFERROR(IF(B34="","",IF(F34="","",F34*I34)),"") | O34: =IFERROR(IF(B34="","",IF(F34="","",M34*F34)),"") | P34: =VLOOKUP(B34,#REF!,17,FALSE) -> #REF!
C35: =IFERROR((IF(B35="","",IF($F$6="","Informar UF / Tabela / Prazo de Pagamento",IF($F$9="","Informar UF / Tabela / Prazo de Pagamento",IF($C$9="","Informar UF / Tabela / Prazo de Pagamento",VLOOKUP(B35,'Tabela 130 '!$A$5:$T$1001,2,FALSE)))))),"REF. NÃO CADASTRADA NA TABELA") | D35: =IF('FOLHA DE PEDIDO '!B35="","",IF(C35="REF. NÃO CADASTRADA NA TABELA","",VLOOKUP(B35,'Tabela 130 '!$A$5:$AI$801,3,FALSE))) | G35: =IFERROR(IF(C35="REF. NÃO CADASTRADA NA TABELA","",IF($C$9="","",IF($F$9="","",IF(B35="","",IF($C$9=119,VLOOKUP(B35,'Tabela 130 '!$A$5:$T$2711,MATCH($F$9,'Tabela 130 '!$A$5:$T$5,0),FALSE),IF($C$9=553,VLOOKUP(B35,#REF!,MATCH($F$9,#REF!,0),FALSE),IF($C$9=552,VLOOKUP(B35,#REF!,MATCH($F$9,#REF!,0),FALSE),IF($C$9=551,VLOOKUP(B35,#REF!,MATCH($F$9,#REF!,0),FALSE))))))))),"REF. NÃO CADASTRADA NA TABELA") | I35: =IFERROR(IF(B35=0,"",(G35-(G35*H35))),"") | J35: =IF(B35="","",IF(C35="REF. NÃO CADASTRADA NA TABELA","",VLOOKUP(B35,#REF!,7,FALSE))) | K35: =IF($F$6="","",IF(B35="","",IF(C35="REF. NÃO CADASTRADA NA TABELA","",IFERROR(VLOOKUP(B35,#REF!,VLOOKUP($F$6,'BASE CONTÁBIL'!N:O,2,FALSE),FALSE),0)))) | L35: =IFERROR(I35*(1+J35%),"") | M35: =IFERROR(IF(B35="","",L35*(1+K35)),"") | N35: =IFERROR(IF(B35="","",IF(F35="","",F35*I35)),"") | O35: =IFERROR(IF(B35="","",IF(F35="","",M35*F35)),"") | P35: =VLOOKUP(B35,#REF!,17,FALSE) -> #REF!
C36: =IFERROR((IF(B36="","",IF($F$6="","Informar UF / Tabela / Prazo de Pagamento",IF($F$9="","Informar UF / Tabela / Prazo de Pagamento",IF($C$9="","Informar UF / Tabela / Prazo de Pagamento",VLOOKUP(B36,'Tabela 130 '!$A$5:$T$1001,2,FALSE)))))),"REF. NÃO CADASTRADA NA TABELA") | D36: =IF('FOLHA DE PEDIDO '!B36="","",IF(C36="REF. NÃO CADASTRADA NA TABELA","",VLOOKUP(B36,'Tabela 130 '!$A$5:$AI$801,3,FALSE))) | G36: =IFERROR(IF(C36="REF. NÃO CADASTRADA NA TABELA","",IF($C$9="","",IF($F$9="","",IF(B36="","",IF($C$9=119,VLOOKUP(B36,'Tabela 130 '!$A$5:$T$2711,MATCH($F$9,'Tabela 130 '!$A$5:$T$5,0),FALSE),IF($C$9=553,VLOOKUP(B36,#REF!,MATCH($F$9,#REF!,0),FALSE),IF($C$9=552,VLOOKUP(B36,#REF!,MATCH($F$9,#REF!,0),FALSE),IF($C$9=551,VLOOKUP(B36,#REF!,MATCH($F$9,#REF!,0),FALSE))))))))),"REF. NÃO CADASTRADA NA TABELA") | I36: =IFERROR(IF(B36=0,"",(G36-(G36*H36))),"") | J36: =IF(B36="","",IF(C36="REF. NÃO CADASTRADA NA TABELA","",VLOOKUP(B36,#REF!,7,FALSE))) | K36: =IF($F$6="","",IF(B36="","",IF(C36="REF. NÃO CADASTRADA NA TABELA","",IFERROR(VLOOKUP(B36,#REF!,VLOOKUP($F$6,'BASE CONTÁBIL'!N:O,2,FALSE),FALSE),0)))) | L36: =IFERROR(I36*(1+J36%),"") | M36: =IFERROR(IF(B36="","",L36*(1+K36)),"") | N36: =IFERROR(IF(B36="","",IF(F36="","",F36*I36)),"") | O36: =IFERROR(IF(B36="","",IF(F36="","",M36*F36)),"") | P36: =VLOOKUP(B36,#REF!,17,FALSE) -> #REF!
C37: =IFERROR((IF(B37="","",IF($F$6="","Informar UF / Tabela / Prazo de Pagamento",IF($F$9="","Informar UF / Tabela / Prazo de Pagamento",IF($C$9="","Informar UF / Tabela / Prazo de Pagamento",VLOOKUP(B37,'Tabela 130 '!$A$5:$T$1001,2,FALSE)))))),"REF. NÃO CADASTRADA NA TABELA") | D37: =IF('FOLHA DE PEDIDO '!B37="","",IF(C37="REF. NÃO CADASTRADA NA TABELA","",VLOOKUP(B37,'Tabela 130 '!$A$5:$AI$801,3,FALSE))) | G37: =IFERROR(IF(C37="REF. NÃO CADASTRADA NA TABELA","",IF($C$9="","",IF($F$9="","",IF(B37="","",IF($C$9=119,VLOOKUP(B37,'Tabela 130 '!$A$5:$T$2711,MATCH($F$9,'Tabela 130 '!$A$5:$T$5,0),FALSE),IF($C$9=553,VLOOKUP(B37,#REF!,MATCH($F$9,#REF!,0),FALSE),IF($C$9=552,VLOOKUP(B37,#REF!,MATCH($F$9,#REF!,0),FALSE),IF($C$9=551,VLOOKUP(B37,#REF!,MATCH($F$9,#REF!,0),FALSE))))))))),"REF. NÃO CADASTRADA NA TABELA") | I37: =IFERROR(IF(B37=0,"",(G37-(G37*H37))),"") | J37: =IF(B37="","",IF(C37="REF. NÃO CADASTRADA NA TABELA","",VLOOKUP(B37,#REF!,7,FALSE))) | K37: =IF($F$6="","",IF(B37="","",IF(C37="REF. NÃO CADASTRADA NA TABELA","",IFERROR(VLOOKUP(B37,#REF!,VLOOKUP($F$6,'BASE CONTÁBIL'!N:O,2,FALSE),FALSE),0)))) | L37: =IFERROR(I37*(1+J37%),"") | M37: =IFERROR(IF(B37="","",L37*(1+K37)),"") | N37: =IFERROR(IF(B37="","",IF(F37="","",F37*I37)),"") | O37: =IFERROR(IF(B37="","",IF(F37="","",M37*F37)),"") | P37: =VLOOKUP(B37,#REF!,17,FALSE) -> #REF!
... C328: =IFERROR((IF(B328="","",IF($F$6="","Informar UF / Tabela / Prazo de Pagamento",IF($F$9="","Informar UF / Tabela / Prazo de Pagamento",IF($C$9="","Informar UF / Tabela / Prazo de Pagamento",VLOOKUP(B328,'Tabela 130 '!$A$5:$T$1001,2,FALSE)))))),"REF. NÃO CADASTRADA NA TABELA") | D328: =IF('FOLHA DE PEDIDO '!B328="","",IF(C328="REF. NÃO CADASTRADA NA TABELA","",VLOOKUP(B328,'Tabela 130 '!$A$5:$AI$801,3,FALSE))) | G328: =IFERROR(IF(C328="REF. NÃO CADASTRADA NA TABELA","",IF($C$9="","",IF($F$9="","",IF(B328="","",IF($C$9=119,VLOOKUP(B328,'Tabela 130 '!$A$5:$T$2711,MATCH($F$9,'Tabela 130 '!$A$5:$T$5,0),FALSE),IF($C$9=553,VLOOKUP(B328,#REF!,MATCH($F$9,#REF!,0),FALSE),IF($C$9=552,VLOOKUP(B328,#REF!,MATCH($F$9,#REF!,0),FALSE),IF($C$9=551,VLOOKUP(B328,#REF!,MATCH($F$9,#REF!,0),FALSE))))))))),"REF. NÃO CADASTRADA NA TABELA") | I328: =IFERROR(IF(B328=0,"",(G328-(G328*H328))),"") | J328: =IF(B328="","",IF(C328="REF. NÃO CADASTRADA NA TABELA","",VLOOKUP(B328,#REF!,7,FALSE))) | K328: =IF($F$6="","",IF(B328="","",IF(C328="REF. NÃO CADASTRADA NA TABELA","",IFERROR(VLOOKUP(B328,#REF!,VLOOKUP($F$6,'BASE CONTÁBIL'!N:O,2,FALSE),FALSE),0)))) | L328: =IFERROR(I328*(1+J328%),"") | M328: =IFERROR(IF(B328="","",L328*(1+K328)),"") | N328: =IFERROR(IF(B328="","",IF(F328="","",F328*I328)),"") | O328: =IFERROR(IF(B328="","",IF(F328="","",M328*F328)),"") | P328: =VLOOKUP(B328,#REF!,17,FALSE) -> #REF!
B330: 8097
B331: 8098
B332: 8099
B333: 8100
B334: 8101
B335: 8102
B336: 8103
B337: 8104
B338: 8105
B339: 8106
B340: 8107
B341: 8108
... B715: 9047

Sheet Tabela 130 
A1: L
J4: PREÇOS UNITÁRIOS
A5: Referência | B5: Descrição | C5: EMB. | D5: À Vista | E5: 14 | F5: 21 | G5: 28 | H5: 35 | I5: 42 | J5: 49 | K5: 56 | L5: 60 | M5: 75 | N5: 90 | O5: MG | P5: PR | Q5: RJ | R5: RS | S5: SP | T5: IPI
A6: 121 | B6: CAIXA RETANGULAR 3,5 L. | C6: 6 | D6: 17.69 | E6: 17.84 | F6: 17.92 | G6: 18 | H6: 18.07 | I6: 18.16 | J6: 18.23 | K6: 18.32 | L6: 18.36 | M6: 18.54 | N6: 18.71
A7: 122 | B7: CAIXA RETANGULAR 6,5 L. | C7: 6 | D7: 25.91 | E7: 26.14 | F7: 26.25 | G7: 26.37 | H7: 26.49 | I7: 26.6 | J7: 26.72 | K7: 26.84 | L7: 26.9 | M7: 27.16 | N7: 27.41
A8: 123 | B8: CAIXA RETANGULAR 11 L. | C8: 6 | D8: 43.73 | E8: 44.12 | F8: 44.31 | G8: 44.51 | H8: 44.71 | I8: 44.9 | J8: 45.1 | K8: 45.29 | L8: 45.41 | M8: 45.84 | N8: 46.27
A9: 125 | B9: BACIA REDONDA 2,5 L. | C9: 12 | D9: 6.49 | E9: 6.54 | F9: 6.57 | G9: 6.6 | H9: 6.62 | I9: 6.66 | J9: 6.69 | K9: 6.72 | L9: 6.73 | M9: 6.79 | N9: 6.86
A10: 126 | B10: BACIA REDONDA 5,5 L. | C10: 12 | D10: 9.12 | E10: 9.2 | F10: 9.23 | G10: 9.28 | H10: 9.32 | I10: 9.36 | J10: 9.4 | K10: 9.45 | L10: 9.47 | M10: 9.55 | N10: 9.65
A11: 127 | B11: BACIA REDONDA 11 L. | C11: 6 | D11: 17.75 | E11: 17.91 | F11: 17.99 | G11: 18.07 | H11: 18.15 | I11: 18.23 | J11: 18.31 | K11: 18.39 | L11: 18.44 | M11: 18.61 | N11: 18.79
A12: 128 | B12: BACIA REDONDA 19,5 L. | C12: 6 | D12: 27.29 | E12: 27.52 | F12: 27.65 | G12: 27.76 | H12: 27.89 | I12: 28.01 | J12: 28.14 | K12: 28.25 | L12: 28.33 | M12: 28.6 | N12: 28.87
A13: 150 | B13: BACIA LISA 2,5 L | C13: 12 | D13: 3.9 | E13: 3.93 | F13: 3.94 | G13: 3.96 | H13: 3.98 | I13: 3.99 | J13: 4.02 | K13: 4.04 | L13: 4.05 | M13: 4.08 | N13: 4.12
A14: 160 | B14: BALDE 8.0 LTS. | C14: 12 | D14: 13.57 | E14: 13.7 | F14: 13.75 | G14: 13.81 | H14: 13.88 | I14: 13.93 | J14: 13.99 | K14: 14.06 | L14: 14.09 | M14: 14.23 | N14: 14.36
A15: 160LP | B15: BALDE RECYCLE 8L. | C15: 12 | D15: 11.64 | E15: 11.75 | F15: 11.79 | G15: 11.84 | H15: 11.9 | I15: 11.95 | J15: 12 | K15: 12.06 | L15: 12.09 | M15: 12.2 | N15: 12.31
A16: 162 | B16: BALDE 16 LTS. | C16: 6 | D16: 25.98 | E16: 26.21 | F16: 26.33 | G16: 26.44 | H16: 26.56 | I16: 26.68 | J16: 26.8 | K16: 26.91 | L16: 26.98 | M16: 27.23 | N16: 27.49
A17: 163 | B17: BALDE 10 LTS. | C17: 12 | D17: 15.74 | E17: 15.88 | F17: 15.94 | G17: 16.02 | H17: 16.09 | I17: 16.16 | J17: 16.23 | K17: 16.31 | L17: 16.35 | M17: 16.5 | N17: 16.66
A18: 163LP | B18: BALDE RECYCLE 1OL. | C18: 12 | D18: 12.27 | E18: 12.38 | F18: 12.43 | G18: 12.49 | H18: 12.55 | I18: 12.6 | J18: 12.65 | K18: 12.71 | L18: 12.74 | M18: 12.87 | N18: 12.98
A19: 164 | B19: LIXAO 97 LITROS. | C19: 4 | D19: 136.96 | E19: 138.17 | F19: 138.78 | G19: 139.39 | H19: 140 | I19: 140.62 | J19: 141.24 | K19: 141.86 | L19: 142.21 | M19: 143.56 | N19: 144.91
A20: 164AM | B20: LIXEIRA 97 LITROS AMARELA | C20: 4 | D20: 171.37 | E20: 172.88 | F20: 173.65 | G20: 174.4 | H20: 175.18 | I20: 175.95 | J20: 176.73 | K20: 177.5 | L20: 177.95 | M20: 179.63 | N20: 181.33
A21: 164AZ | B21: LIXEIRA 97 LITROS AZUL. | C21: 4 | D21: 171.37 | E21: 172.88 | F21: 173.65 | G21: 174.4 | H21: 175.18 | I21: 175.95 | J21: 176.73 | K21: 177.5 | L21: 177.95 | M21: 179.63 | N21: 181.33
A22: 164LP | B22: LIXEIRA 97 LITROS PRETO. | C22: 4 | D22: 109.55 | E22: 110.5 | F22: 110.99 | G22: 111.48 | H22: 111.97 | I22: 112.46 | J22: 112.96 | K22: 113.45 | L22: 113.74 | M22: 114.82 | N22: 115.9
A23: 164VD | B23: LIXEIRA 97 LITROS VERDE. | C23: 4 | D23: 171.37 | E23: 172.88 | F23: 173.65 | G23: 174.4 | H23: 175.18 | I23: 175.95 | J23: 176.73 | K23: 177.5 | L23: 177.95 | M23: 179.63 | N23: 181.33
A24: 164VM | B24: LIXEIRA 97 LITROS VERMELH | C24: 4 | D24: 171.37 | E24: 172.88 | F24: 173.65 | G24: 174.4 | H24: 175.18 | I24: 175.95 | J24: 176.73 | K24: 177.5 | L24: 177.95 | M24: 179.63 | N24: 181.33
A25: 167 | B25: CESTO PARA ROUPAS 35 L. | C25: 6 | D25: 24.54 | E25: 24.76 | F25: 24.87 | G25: 24.97 | H25: 25.08 | I25: 25.2 | J25: 25.3 | K25: 25.42 | L25: 25.49 | M25: 25.72 | N25: 25.96
A26: 167LP | B26: CESTO PARA ROUPAS 35 L. | C26: 6 | D26: 17.69 | E26: 17.84 | F26: 17.92 | G26: 18 | H26: 18.07 | I26: 18.16 | J26: 18.23 | K26: 18.32 | L26: 18.36 | M26: 18.54 | N26: 18.71
A27: 168 | B27: BALDE 20 LITROS. | C27: 6 | D27: 27.29 | E27: 27.52 | F27: 27.65 | G27: 27.76 | H27: 27.89 | I27: 28.01 | J27: 28.14 | K27: 28.25 | L27: 28.33 | M27: 28.6 | N27: 28.87
A28: 170 | B28: LIXEIRA BASCULANTE P/PIA. | C28: 6 | D28: 12.2 | E28: 12.31 | F28: 12.36 | G28: 12.42 | H28: 12.47 | I28: 12.52 | J28: 12.58 | K28: 12.64 | L28: 12.67 | M28: 12.79 | N28: 12.91
A29: 171 | B29: LIXEIRA P/ PIA. | C29: 12 | D29: 9.03 | E29: 9.12 | F29: 9.16 | G29: 9.19 | H29: 9.23 | I29: 9.28 | J29: 9.32 | K29: 9.36 | L29: 9.38 | M29: 9.47 | N29: 9.56
A30: 173 | B30: CESTO P/ PAPEL. | C30: 12 | D30: 6.84 | E30: 6.9 | F30: 6.93 | G30: 6.97 | H30: 7 | I30: 7.03 | J30: 7.05 | K30: 7.08 | L30: 7.1 | M30: 7.17 | N30: 7.24
A31: 175 | B31: LIXEIRA 35 LITROS. | C31: 4 | D31: 54.7 | E31: 55.19 | F31: 55.42 | G31: 55.67 | H31: 55.91 | I31: 56.16 | J31: 56.41 | K31: 56.66 | L31: 56.8 | M31: 57.34 | N31: 57.88
A32: 177 | B32: LIXEIRA 62 LITROS. | C32: 4 | D32: 75.4 | E32: 76.07 | F32: 76.4 | G32: 76.74 | H32: 77.07 | I32: 77.41 | J32: 77.76 | K32: 78.1 | L32: 78.3 | M32: 79.03 | N32: 79.78
A33: 179 | B33: LIXEIRA BASCULANTE 12 LTR | C33: 6 | D33: 27.29 | E33: 27.52 | F33: 27.65 | G33: 27.76 | H33: 27.89 | I33: 28.01 | J33: 28.14 | K33: 28.25 | L33: 28.33 | M33: 28.6 | N33: 28.87
A34: 182 | B34: LIXEIRA C/PEDAL 13 LITROS | C34: 6 | D34: 35.51 | E34: 35.83 | F34: 35.98 | G34: 36.14 | H34: 36.3 | I34: 36.45 | J34: 36.61 | K34: 36.77 | L34: 36.87 | M34: 37.22 | N34: 37.57
A35: 183 | B35: LIXEIRA C/PEDAL 6,5L | C35: 6 | D35: 24.54 | E35: 24.76 | F35: 24.87 | G35: 24.97 | H35: 25.08 | I35: 25.2 | J35: 25.3 | K35: 25.42 | L35: 25.49 | M35: 25.72 | N35: 25.96
A36: 187 | B36: LIXEIRA RETRATIL 1,4 L. | C36: 12 | D36: 8.91 | E36: 8.99 | F36: 9.03 | G36: 9.07 | H36: 9.11 | I36: 9.15 | J36: 9.19 | K36: 9.23 | L36: 9.25 | M36: 9.34 | N36: 9.43
A37: 189 | B37: LIXEIRA RETRATIL 4,1 L. | C37: 9 | D37: 15.02 | E37: 15.14 | F37: 15.21 | G37: 15.28 | H37: 15.35 | I37: 15.41 | J37: 15.49 | K37: 15.55 | L37: 15.59 | M37: 15.74 | N37: 15.88
A38: 191 | B38: POTE HERMETICO 0,5 L. | C38: 12 | D38: 5.06 | E38: 5.1 | F38: 5.12 | G38: 5.14 | H38: 5.18 | I38: 5.2 | J38: 5.22 | K38: 5.24 | L38: 5.25 | M38: 5.3 | N38: 5.36
... A56: 293 | B56: ORGANIZADOR 12,5 LITROS. | C56: 4 | D56: 35.51 | E56: 35.83 | F56: 35.98 | G56: 36.14 | H56: 36.3 | I56: 36.45 | J56: 36.61 | K56: 36.77 | L56: 36.87 | M56: 37.22 | N56: 37.57
A57: 293OC | B57: ORGANIZADOR 12,5 LITROS. | C57: 4 | D57: 25.91 | E57: 26.14 | F57: 26.25 | G57: 26.37 | H57: 26.49 | I57: 26.6 | J57: 26.72 | K57: 26.84 | L57: 26.9 | M57: 27.16 | N57: 27.41
A58: 295 | B58: ORGANIZADOR 38 LITROS. | C58: 4 | D58: 61.56 | E58: 62.1 | F58: 62.38 | G58: 62.64 | H58: 62.92 | I58: 63.2 | J58: 63.47 | K58: 63.76 | L58: 63.92 | M58: 64.52 | N58: 65.14
A59: 295OC | B59: ORGANIZADOR 38 LITROS. | C59: 4 | D59: 40.99 | E59: 41.35 | F59: 41.54 | G59: 41.72 | H59: 41.9 | I59: 42.09 | J59: 42.27 | K59: 42.46 | L59: 42.57 | M59: 42.96 | N59: 43.38
A60: 301 | B60: POTE FREEZER/MICROONDAS 1 | C60: 12 | D60: 6.84 | E60: 6.9 | F60: 6.93 | G60: 6.97 | H60: 7 | I60: 7.03 | J60: 7.05 | K60: 7.08 | L60: 7.1 | M60: 7.17 | N60: 7.24
A61: 301BK | B61: POTE FREEZER/MICROONDAS 1 | C61: 12 | D61: 3.81 | E61: 3.84 | F61: 3.86 | G61: 3.88 | H61: 3.9 | I61: 3.91 | J61: 3.93 | K61: 3.95 | L61: 3.96 | M61: 3.99 | N61: 4.03
A62: 302 | B62: POTE FREEZER/MICROONDAS 2 | C62: 12 | D62: 9.53 | E62: 9.62 | F62: 9.66 | G62: 9.7 | H62: 9.74 | I62: 9.79 | J62: 9.83 | K62: 9.87 | L62: 9.89 | M62: 9.99 | N62: 10.09
A63: 303 | B63: POTE FREEZER/MICROONDAS 3 | C63: 6 | D63: 11.36 | E63: 11.47 | F63: 11.51 | G63: 11.57 | H63: 11.62 | I63: 11.67 | J63: 11.72 | K63: 11.77 | L63: 11.8 | M63: 11.92 | N63: 12.02
A64: 311 | B64: POTE FREEZER/MICROONDAS 0 | C64: 12 | D64: 6.38 | E64: 6.43 | F64: 6.46 | G64: 6.49 | H64: 6.52 | I64: 6.55 | J64: 6.57 | K64: 6.6 | L64: 6.62 | M64: 6.68 | N64: 6.74
A65: 312 | B65: POTE FREEZER/MICROONDAS 1 | C65: 12 | D65: 7.8 | E65: 7.87 | F65: 7.9 | G65: 7.93 | H65: 7.98 | I65: 8.01 | J65: 8.04 | K65: 8.08 | L65: 8.1 | M65: 8.18 | N65: 8.25
A66: 313 | B66: POTE FREEZER/MICROONDAS 2 | C66: 6 | D66: 10.89 | E66: 10.99 | F66: 11.04 | G66: 11.1 | H66: 11.14 | I66: 11.19 | J66: 11.24 | K66: 11.29 | L66: 11.32 | M66: 11.43 | N66: 11.53
A67: 314 | B67: POTE MARMITA WAVE 1,2L. | C67: 6 | D67: 10.27 | E67: 10.36 | F67: 10.41 | G67: 10.45 | H67: 10.5 | I67: 10.54 | J67: 10.59 | K67: 10.64 | L67: 10.66 | M67: 10.77 | N67: 10.86
A68: 322 | B68: POTE FREEZER/MICROONDAS 0 | C68: 12 | D68: 5.15 | E68: 5.2 | F68: 5.22 | G68: 5.25 | H68: 5.27 | I68: 5.29 | J68: 5.31 | K68: 5.34 | L68: 5.36 | M68: 5.4 | N68: 5.45
A69: 324 | B69: POTE FREEZER/MICROONDAS 1 | C69: 12 | D69: 6.43 | E69: 6.49 | F69: 6.52 | G69: 6.54 | H69: 6.57 | I69: 6.6 | J69: 6.63 | K69: 6.66 | L69: 6.68 | M69: 6.74 | N69: 6.81
A70: 331 | B70: POTE FREEZER/MICROONDAS 0 | C70: 12 | D70: 4.73 | E70: 4.77 | F70: 4.79 | G70: 4.81 | H70: 4.84 | I70: 4.86 | J70: 4.88 | K70: 4.9 | L70: 4.91 | M70: 4.96 | N70: 5.01
A71: 334 | B71: POTE FREEZER/MICROONDAS 2 | C71: 6 | D71: 10.28 | E71: 10.37 | F71: 10.42 | G71: 10.47 | H71: 10.51 | I71: 10.55 | J71: 10.61 | K71: 10.65 | L71: 10.68 | M71: 10.78 | N71: 10.88
A72: 351 | B72: BACIA CANELADA 2,5 L. | C72: 12 | D72: 5.96 | E72: 6.02 | F72: 6.04 | G72: 6.07 | H72: 6.09 | I72: 6.12 | J72: 6.15 | K72: 6.18 | L72: 6.19 | M72: 6.25 | N72: 6.32
A73: 352 | B73: BACIA CANELADA 4,9 L. | C73: 12 | D73: 8.16 | E73: 8.23 | F73: 8.26 | G73: 8.31 | H73: 8.34 | I73: 8.37 | J73: 8.41 | K73: 8.45 | L73: 8.47 | M73: 8.55 | N73: 8.63
... A75: 354 | B75: BACIA CANELADA 13,5 L. | C75: 12 | D75: 16.38 | E75: 16.53 | F75: 16.6 | G75: 16.68 | H75: 16.74 | I75: 16.82 | J75: 16.89 | K75: 16.97 | L75: 17.01 | M75: 17.17 | N75: 17.34
A76: 354LP | B76: BACIA CANELADA 13,5 L. | C76: 12 | D76: 13.64 | E76: 13.76 | F76: 13.82 | G76: 13.89 | H76: 13.94 | I76: 14 | J76: 14.07 | K76: 14.13 | L76: 14.16 | M76: 14.3 | N76: 14.43
A77: 355 | B77: BACIA CANELADA 34 L. | C77: 4 | D77: 38.25 | E77: 38.58 | F77: 38.76 | G77: 38.93 | H77: 39.1 | I77: 39.27 | J77: 39.45 | K77: 39.62 | L77: 39.71 | M77: 40.1 | N77: 40.47
A78: 355LP | B78: BACIA CANELADA 34 L. | C78: 4 | D78: 30.02 | E78: 30.29 | F78: 30.43 | G78: 30.55 | H78: 30.69 | I78: 30.82 | J78: 30.96 | K78: 31.1 | L78: 31.17 | M78: 31.47 | N78: 31.77
A79: 360 | B79: BALDE 8.0 LTS 2 BICOS. | C79: 12 | D79: 17.69 | E79: 17.84 | F79: 17.92 | G79: 18 | H79: 18.07 | I79: 18.16 | J79: 18.23 | K79: 18.32 | L79: 18.36 | M79: 18.54 | N79: 18.71
A80: 368 | B80: PULVERIZADOR MULTIUSO. | C80: 20 | D80: 7.8 | E80: 7.87 | F80: 7.9 | G80: 7.93 | H80: 7.98 | I80: 8.01 | J80: 8.04 | K80: 8.08 | L80: 8.1 | M80: 8.18 | N80: 8.25
A81: 375LP | B81: LIXEIRA RECYCLE 35L. | C81: 4 | D81: 36.88 | E81: 37.2 | F81: 37.37 | G81: 37.53 | H81: 37.7 | I81: 37.86 | J81: 38.03 | K81: 38.2 | L81: 38.3 | M81: 38.66 | N81: 39.02
A82: 377LP | B82: LIXEIRA RECYCLE 62L | C82: 4 | D82: 64.29 | E82: 64.87 | F82: 65.16 | G82: 65.43 | H82: 65.72 | I82: 66.02 | J82: 66.31 | K82: 66.59 | L82: 66.76 | M82: 67.39 | N82: 68.03
A83: 381 | B83: SALEIRO DE MESA | C83: 24 | D83: 6.63 | E83: 6.7 | F83: 6.72 | G83: 6.75 | H83: 6.78 | I83: 6.82 | J83: 6.85 | K83: 6.87 | L83: 6.89 | M83: 6.95 | N83: 7.02
A84: 382 | B84: PALITEIRO | C84: 24 | D84: 6.63 | E84: 6.7 | F84: 6.72 | G84: 6.75 | H84: 6.78 | I84: 6.82 | J84: 6.85 | K84: 6.87 | L84: 6.89 | M84: 6.95 | N84: 7.02
A85: 385 | B85: KIT 3 BISNAGA 0,250ML | C85: 30 | D85: 8.19 | E85: 8.25 | F85: 8.3 | G85: 8.33 | H85: 8.37 | I85: 8.4 | J85: 8.45 | K85: 8.48 | L85: 8.5 | M85: 8.58 | N85: 8.66
A86: 386 | B86: TABUA RETANGULAR P/CORTE. | C86: 6 | D86: 25.37 | E86: 25.59 | F86: 25.7 | G86: 25.82 | H86: 25.92 | I86: 26.04 | J86: 26.16 | K86: 26.27 | L86: 26.34 | M86: 26.58 | N86: 26.84
A87: 389 | B87: BISNAGA 250ML | C87: 50 | D87: 3.28 | E87: 3.3 | F87: 3.32 | G87: 3.33 | H87: 3.34 | I87: 3.37 | J87: 3.38 | K87: 3.4 | L87: 3.4 | M87: 3.43 | N87: 3.47
A88: 400 | B88: CONJ.5 POTES QUADRADOS. | C88: 6 | D88: 47.85 | E88: 48.27 | F88: 48.48 | G88: 48.69 | H88: 48.9 | I88: 49.13 | J88: 49.34 | K88: 49.55 | L88: 49.68 | M88: 50.15 | N88: 50.63
A89: 401 | B89: POTE 0,5L | C89: 12 | D89: 5.21 | E89: 5.25 | F89: 5.28 | G89: 5.3 | H89: 5.33 | I89: 5.35 | J89: 5.37 | K89: 5.4 | L89: 5.41 | M89: 5.46 | N89: 5.52
A90: 402 | B90: POTE 1,3L | C90: 12 | D90: 7.48 | E90: 7.54 | F90: 7.57 | G90: 7.6 | H90: 7.64 | I90: 7.67 | J90: 7.7 | K90: 7.74 | L90: 7.75 | M90: 7.83 | N90: 7.9
A91: 403 | B91: POTE 2,3L | C91: 12 | D91: 10.96 | E91: 11.05 | F91: 11.1 | G91: 11.15 | H91: 11.19 | I91: 11.25 | J91: 11.3 | K91: 11.34 | L91: 11.37 | M91: 11.48 | N91: 11.59
A92: 404 | B92: POTE 4,5L | C92: 6 | D92: 19.05 | E92: 19.22 | F92: 19.31 | G92: 19.39 | H92: 19.48 | I92: 19.56 | J92: 19.65 | K92: 19.73 | L92: 19.79 | M92: 19.98 | N92: 20.16
A93: 405 | B93: POTE 8L | C93: 6 | D93: 23.17 | E93: 23.38 | F93: 23.47 | G93: 23.58 | H93: 23.69 | I93: 23.79 | J93: 23.89 | K93: 23.99 | L93: 24.06 | M93: 24.28 | N93: 24.52
A94: 425 | B94: FEIRINHA 90 ITENS. | C94: 1 | D94: 294.76 | E94: 297.36 | F94: 298.67 | G94: 299.98 | H94: 301.3 | I94: 302.63 | J94: 303.96 | K94: 305.3 | L94: 306.07 | M94: 308.96 | N94: 311.89
... A102: 514 | B102: ESPREMEDOR DE FRUTAS 0,5 | C102: 12 | D102: 8.21 | E102: 8.29 | F102: 8.32 | G102: 8.36 | H102: 8.39 | I102: 8.43 | J102: 8.47 | K102: 8.51 | L102: 8.53 | M102: 8.61 | N102: 8.69
A103: 517LP | B103: CESTO RECYCLE 55L. | C103: 6 | D103: 38.25 | E103: 38.58 | F103: 38.76 | G103: 38.93 | H103: 39.1 | I103: 39.27 | J103: 39.45 | K103: 39.62 | L103: 39.71 | M103: 40.1 | N103: 40.47
A104: 519 | B104: LAVADOR ARROZ. | C104: 12 | D104: 7.92 | E104: 8 | F104: 8.03 | G104: 8.06 | H104: 8.1 | I104: 8.14 | J104: 8.17 | K104: 8.21 | L104: 8.23 | M104: 8.31 | N104: 8.38
A105: 521 | B105: BANDEJA 2,2 L. | C105: 12 | D105: 5.88 | E105: 5.93 | F105: 5.96 | G105: 5.99 | H105: 6.02 | I105: 6.04 | J105: 6.06 | K105: 6.09 | L105: 6.1 | M105: 6.17 | N105: 6.22
A106: 522 | B106: BANDEJA 7 L. | C106: 12 | D106: 13.64 | E106: 13.76 | F106: 13.82 | G106: 13.89 | H106: 13.94 | I106: 14 | J106: 14.07 | K106: 14.13 | L106: 14.16 | M106: 14.3 | N106: 14.43
A107: 523 | B107: BANDEJA RETANGULAR 17L | C107: 6 | D107: 28.65 | E107: 28.9 | F107: 29.03 | G107: 29.16 | H107: 29.29 | I107: 29.42 | J107: 29.54 | K107: 29.68 | L107: 29.76 | M107: 30.03 | N107: 30.32
A108: 528 | B108: PA PARA LIXO. | C108: 24 | D108: 4.8 | E108: 4.85 | F108: 4.87 | G108: 4.89 | H108: 4.91 | I108: 4.93 | J108: 4.95 | K108: 4.97 | L108: 4.98 | M108: 5.03 | N108: 5.08
A109: 531 | B109: SABONETEIRA P/VIAGEM. | C109: 18 | D109: 2.86 | E109: 2.89 | F109: 2.91 | G109: 2.92 | H109: 2.93 | I109: 2.94 | J109: 2.95 | K109: 2.97 | L109: 2.97 | M109: 3 | N109: 3.04
A110: 538 | B110: FARINHEIRA/ACUCAREIRO 0,9 | C110: 12 | D110: 7.92 | E110: 8 | F110: 8.03 | G110: 8.06 | H110: 8.1 | I110: 8.14 | J110: 8.17 | K110: 8.21 | L110: 8.23 | M110: 8.31 | N110: 8.38
A111: 541 | B111: POTE FREEZER/MICROONDAS 0 | C111: 12 | D111: 6.17 | E111: 6.22 | F111: 6.25 | G111: 6.28 | H111: 6.3 | I111: 6.34 | J111: 6.36 | K111: 6.39 | L111: 6.41 | M111: 6.46 | N111: 6.53
A112: 542 | B112: POTE FREEZER/MICROONDAS 1 | C112: 12 | D112: 7.88 | E112: 7.96 | F112: 7.99 | G112: 8.02 | H112: 8.06 | I112: 8.09 | J112: 8.13 | K112: 8.17 | L112: 8.19 | M112: 8.26 | N112: 8.34
A113: 542CA | B113: POTE DECOR CAFE. | C113: 12 | D113: 10.89 | E113: 10.99 | F113: 11.04 | G113: 11.1 | H113: 11.14 | I113: 11.19 | J113: 11.24 | K113: 11.29 | L113: 11.32 | M113: 11.43 | N113: 11.53
A114: 542AC | B114: POTE DECOR ACUCAR. | C114: 12 | D114: 10.89 | E114: 10.99 | F114: 11.04 | G114: 11.1 | H114: 11.14 | I114: 11.19 | J114: 11.24 | K114: 11.29 | L114: 11.32 | M114: 11.43 | N114: 11.53
A115: 543 | B115: POTE FREEZER/MICROONDAS 2 | C115: 6 | D115: 10.94 | E115: 11.03 | F115: 11.09 | G115: 11.13 | H115: 11.18 | I115: 11.24 | J115: 11.28 | K115: 11.33 | L115: 11.36 | M115: 11.47 | N115: 11.58
A116: 543MA | B116: POTE DECOR MATE PLASVALE | C116: 6 | D116: 13.02 | E116: 13.14 | F116: 13.2 | G116: 13.26 | H116: 13.31 | I116: 13.38 | J116: 13.43 | K116: 13.49 | L116: 13.53 | M116: 13.65 | N116: 13.78
A117: 544 | B117: POTE FREEZER/MICROONDAS 4 | C117: 6 | D117: 15.71 | E117: 15.85 | F117: 15.92 | G117: 15.99 | H117: 16.06 | I117: 16.13 | J117: 16.2 | K117: 16.27 | L117: 16.32 | M117: 16.46 | N117: 16.62
A118: 545 | B118: POTE FREEZER/MICROONDAS 7 | C118: 6 | D118: 24.61 | E118: 24.83 | F118: 24.93 | G118: 25.05 | H118: 25.16 | I118: 25.26 | J118: 25.38 | K118: 25.49 | L118: 25.55 | M118: 25.79 | N118: 26.04
A119: 562 | B119: POTE FREEZER/MICROONDAS 0 | C119: 12 | D119: 5.44 | E119: 5.5 | F119: 5.52 | G119: 5.54 | H119: 5.56 | I119: 5.59 | J119: 5.61 | K119: 5.63 | L119: 5.66 | M119: 5.71 | N119: 5.76
A120: 563 | B120: POTE FREEZER/MICROONDAS 1 | C120: 12 | D120: 7.48 | E120: 7.54 | F120: 7.57 | G120: 7.6 | H120: 7.64 | I120: 7.67 | J120: 7.7 | K120: 7.74 | L120: 7.75 | M120: 7.83 | N120: 7.9
A121: 564 | B121: POTE FREEZER/MICROONDAS 2 | C121: 12 | D121: 10.89 | E121: 10.99 | F121: 11.04 | G121: 11.1 | H121: 11.14 | I121: 11.19 | J121: 11.24 | K121: 11.29 | L121: 11.32 | M121: 11.43 | N121: 11.53
A122: 604 | B122: POTE 1,25 LTS. | C122: 12 | D122: 8.21 | E122: 8.29 | F122: 8.32 | G122: 8.36 | H122: 8.39 | I122: 8.43 | J122: 8.47 | K122: 8.51 | L122: 8.53 | M122: 8.61 | N122: 8.69
A123: 612 | B123: SANDUICHEIRA | C123: 12 | D123: 4.05 | E123: 4.08 | F123: 4.1 | G123: 4.11 | H123: 4.13 | I123: 4.15 | J123: 4.17 | K123: 4.19 | L123: 4.2 | M123: 4.24 | N123: 4.28
A124: 612DC | B124: SANDUICHEIRA PLASVALE DEC | C124: 12 | D124: 5.44 | E124: 5.5 | F124: 5.52 | G124: 5.54 | H124: 5.56 | I124: 5.59 | J124: 5.61 | K124: 5.63 | L124: 5.66 | M124: 5.71 | N124: 5.76
A125: 617 | B125: GARRAFA 1L. | C125: 12 | D125: 10.28 | E125: 10.37 | F125: 10.42 | G125: 10.47 | H125: 10.51 | I125: 10.55 | J125: 10.61 | K125: 10.65 | L125: 10.68 | M125: 10.78 | N125: 10.88
A126: 618 | B126: GARRAFA 2 L | C126: 12 | D126: 12.27 | E126: 12.38 | F126: 12.43 | G126: 12.49 | H126: 12.55 | I126: 12.6 | J126: 12.65 | K126: 12.71 | L126: 12.74 | M126: 12.87 | N126: 12.98
A127: 618. | B127: GARRAFA 2 L | C127: 12 | D127: 8.88 | E127: 8.96 | F127: 9 | G127: 9.04 | H127: 9.08 | I127: 9.12 | J127: 9.16 | K127: 9.2 | L127: 9.22 | M127: 9.31 | N127: 9.4
...

Sheet BASE CONTÁBIL
A1: CLASSIFICAÇÃO FISCAL | B1: REVENDA | G1: NACIONAL
B2: MG | C2: PR | D2: RJ | E2: RS | F2: SP | G2: MG | H2: PR | I2: RJ | J2: RS | K2: SP | N2: MG | O2: 32
A3: 39221000 | B3: 0 | C3: 0 | D3: 0 | E3: 0 | F3: 0 | G3: 0 | H3: 0 | I3: 0 | J3: 0 | K3: 0 | N3: PR | O3: 33
A4: 39241000 | B4: 0.2526 | C4: 0.3673 | D4: 0.3817 | E4: 0 | F4: 0.3231 | G4: 0.1781 | H4: 0.2584 | I4: 0.2724 | J4: 0 | K4: 0.2179 | N4: RJ | O4: 34
A5: 39249000 | B5: 0 | C5: 0 | D5: 0 | E5: 0 | F5: 0 | G5: 0 | H5: 0 | I5: 0 | J5: 0 | K5: 0 | N5: RS | O5: 35
A6: 39269090 | B6: 0 | C6: 0 | D6: 0 | E6: 0 | F6: 0 | G6: 0 | H6: 0 | I6: 0 | J6: 0 | K6: 0 | N6: SP | O6: 36
A7: 39232910 | B7: 0 | C7: 0 | D7: 0 | E7: 0 | F7: 0 | G7: 0 | H7: 0 | I7: 0 | J7: 0 | K7: 0
A8: 42010090 | B8: 0 | C8: 0 | D8: 0 | E8: 0 | F8: 0 | G8: 0 | H8: 0 | I8: 0 | J8: 0 | K8: 0
A9: 42022220 | B9: 0 | C9: 0 | D9: 0 | E9: 0 | F9: 0 | G9: 0 | H9: 0 | I9: 0 | J9: 0 | K9: 0
A10: 42022900 | B10: 0 | C10: 0 | D10: 0 | E10: 0 | F10: 0 | G10: 0 | H10: 0 | I10: 0 | J10: 0 | K10: 0
A11: 44191900 | B11: 0 | C11: 0 | D11: 0 | E11: 0 | F11: 0 | G11: 0 | H11: 0 | I11: 0 | J11: 0 | K11: 0
A12: 44191100 | B12: 0 | C12: 0 | D12: 0 | E12: 0 | F12: 0 | G12: 0 | H12: 0 | I12: 0 | J12: 0 | K12: 0
A13: 48191000 | B13: 0 | C13: 0 | D13: 0 | E13: 0 | F13: 0 | G13: 0 | H13: 0 | I13: 0 | J13: 0 | K13: 0
A14: 57023200 | B14: 0 | C14: 0 | D14: 0 | E14: 0 | F14: 0 | G14: 0 | H14: 0 | I14: 0 | J14: 0 | K14: 0
A15: 61169300 | B15: 0 | C15: 0 | D15: 0 | E15: 0 | F15: 0 | G15: 0 | H15: 0 | I15: 0 | J15: 0 | K15: 0
A16: 63079090 | B16: 0 | C16: 0 | D16: 0 | E16: 0 | F16: 0 | G16: 0 | H16: 0 | I16: 0 | J16: 0 | K16: 0
A17: 70109012 | B17: 0 | C17: 0 | D17: 0 | E17: 0 | F17: 0 | G17: 0 | H17: 0 | I17: 0 | J17: 0 | K17: 0
A18: 70133700 | B18: 0.3223 | C18: 0.3302 | D18: 0.3519 | E18: 0 | F18: 0.2773 | G18: 0 | H18: 0 | I18: 0 | J18: 0 | K18: 0
... A32: 70132800 | B32: 0.3223 | C32: 0.3451 | D32: 0.3756 | E32: 0 | F32: 0.3234 | G32: 0 | H32: 0 | I32: 0 | J32: 0 | K32: 0
A33: 70134210 | B33: 32,35% | C33: 0.344 | D33: 0.3756 | E33: 0.2897 | F33: 0.3223 | G33: 0 | H33: 0 | I33: 0 | J33: 0 | K33: 0
A34: 70109090 | B34: 0 | C34: 0 | D34: 0 | E34: 0 | F34: 0 | G34: 0 | H34: 0 | I34: 0 | J34: 0 | K34: 0
A35: 70109022 | B35: 0 | C35: 0 | D35: 0 | E35: 0 | F35: 0 | G35: 0 | H35: 0 | I35: 0 | J35: 0 | K35: 0
A36: 70109021 | B36: 0 | C36: 0 | D36: 0 | E36: 0 | F36: 0 | G36: 0 | H36: 0 | I36: 0 | J36: 0 | K36: 0
C38: Comparativo ST por UF
C40: NCM | D40: MVA/IVA ORIG. | E40: MVA/IVA AJUST | F40: UF | G40: CUSTO ST
C41: 3924.10.00 | D41: 0.5 | E41: 0.7561 | F41: MG | G41: 0.2785
B42: NACIONAL | C42: 3924.10.00 | D42: 0.5 | E42: 0.6098 | F42: MG | G42: 0.1771
C43: 7013.28.00 | D43: 0.7 | E43: 0.9902 | F43: MG | G43: 0.3218
C44: 7013.37.00 | D44: 0.7 | E44: 0.9902 | F44: MG | G44: 0.3218
C45: 7013.42.90 | D45: 0.7 | E45: 0.9902 | F45: MG | G45: 0.3207
C46: 7013.49.00 | D46: 0.7 | E46: 0.9902 | F46: MG | G46: 0.3207
C47: 8509.40.90 | D47: 0.4 | E47: 0.639 | F47: MG | G47: 0.2575
C48: 8516.79.90 | D48: 0.4 | E48: 0.639 | F48: MG | G48: 0.2586
B49: NACIONAL | C49: 3924.10.00 | D49: 0.5 | E49: 0.6807 | F49: MS | G49: 0.22
C50: 3924.10.00 | D50: 0.5 | E50: 0.7349 | F50: MS | G50: 0.2574
C51: 3924.10.00 | D51: 0.7977 | E51: 1.1046 | F51: PR | G51: 0.3413
C52: 3924.10.00 | D52: 0.7977 | E52: 0.9292 | F52: PR | G52: 0.2346
B53: NACIONAL SN | C53: 3924.10.00 | D53: 0.2393 | E53: 0.2788 | F53: PR | G53: 0.1175
B54: IMPORTADO SN | C54: 3924.10.00 | D54: 0.2393 | E54: 0.3314 | F54: PR | G54: 0.2021
C55: 7013.28.00 | D55: 0.6943 | E55: 0.9836 | F55: PR | G55: 0.3206
C56: 7013.37.00 | D56: 0.6283 | E56: 0.9063 | F56: PR | G56: 0.3067
C57: 7013.42.90 | D57: 1.0653 | E57: 1.4179 | F57: PR | G57: 0.3977
C58: 7013.49.00 | D58: 0.6943 | E58: 0.9836 | F58: PR | G58: 0.3195
C59: 8509.40.90 | D59: 0.4 | E59: 0.639 | F59: PR | G59: 0.2575
C60: 8516.79.90 | D60: 0.43 | E60: 0.6741 | F60: PR | G60: 0.2649
C61: 3924.10.00 | D61: 0.7456 | E61: 1.0947 | F61: RJ | G61: 0.3814
C62: 3924.10.00 | D62: 0.7456 | E62: 0.9202 | F62: RJ | G62: 0.2714
C63: 7013.28.00 | D63: 0.7101 | E63: 1.0521 | F63: RJ | G63: 0.374
C64: 7013.37.00 | D64: 0.6159 | E64: 0.9391 | F64: RJ | G64: 0.3514
C65: 7013.42.90 | D65: 0.9021 | E65: 1.2825 | F65: RJ | G65: 0.4189
C66: 7013.49.00 | D66: 0.7101 | E66: 1.0521 | F66: RJ | G66: 0.3729
... C85: 8516.79.90 | D85: 0.45 | E85: 0.6976 | F85: SP | G85: 0.2691
C87: SN PR | D87: SN = SIMPLES NACIONAL, MVA REDUZIDA EM 70% DA ORIGINAL
D88: ATUALIZADO EM 03/01/2023
E89: REVENDA IMPORTADO
E90: NO CASO DO MS NÃO ANTECIPAMOS, E NÃO HÁ PROTOCO/CONVENIO ENTRE AS UF DE SC E MS.
C93: CST - Código de Substituição Tributária
C95: Código | D95: Origem da mercadoria
C96: 0 | D96: Nacional
C97: 1 | D97: Estrangeiro adquirido direto
C98: 2 | D98: Estrangeiro, adquirido no mercado nacional
C99: 5 | D99: Nacional, com importação inferior ou igual a 40%
C101: OBS.: Os códigos são compostos por três números, acrescentar "00" ao final de todos.
